[
  {
    "character_name": "水戸たん",
    "store_name": "水戸駅店",
    "detail_url": "https://biccame.jp/profile/mito.html",
    "key": "mito",
    "description": "ビックカメラ水戸駅店の擬人化キャラクター。わら納豆のようなツインテールが特徴（実は納豆として食べられるらしい...。）水戸市の花・梅の花の小物が好き。戦車のような靴を履いている。少しおっとりしているが、水戸を盛り上げようと色々なPR活動をしている。",
    "twitter_url": "https://twitter.com/biccameramito",
    "profile_image_url": "https://biccame.jp/profile/images/mito1.png",
    "zipcode": "310-0015",
    "address": "茨城県水戸市宮町1-7-31",
    "store_birthday": "2011-06-23",
    "store_link": "https://www.biccamera.com/bc/i/shop/shoplist/shop115.jsp",
    "image_urls": [
      "https://biccame.jp/profile/images/mito_img.png",
      "https://biccame.jp/profile/images/mito_img_sd.png",
      "https://biccame.jp/profile/images/mito4.png",
      "https://biccame.jp/profile/images/mito5.png"
    ]
  },
  {
    "character_name": "柏たん",
    "store_name": "柏店",
    "detail_url": "https://biccame.jp/profile/kashiwa.html",
    "key": "kashiwa",
    "description": "ビックカメラ柏店の擬人化キャラクター。メガネと柏餅のような頭が特徴。大好物はもちろんモチモチの柏餅！制服のリボンは柏市の木・柏の葉っぱと、市の花・シバザクラがモチーフになっている。",
    "twitter_url": "https://twitter.com/bic_kashiwa",
    "profile_image_url": "https://biccame.jp/profile/images/kashiwa1.png",
    "zipcode": "277-0005",
    "address": "千葉県柏市柏1-1-20",
    "store_birthday": "2005-03-10",
    "store_link": "http://www.biccamera.co.jp/shoplist/shop-035.html",
    "image_urls": [
      "https://biccame.jp/profile/images/kasiwa_img.png",
      "https://biccame.jp/profile/images/kasiwa_img_sd.png",
      "https://biccame.jp/profile/images/kashiwa4.png",
      "https://biccame.jp/profile/images/kashiwa5.png"
    ]
  },
  {
    "character_name": "八王子たん",
    "store_name": "JR八王子駅店",
    "detail_url": "https://biccame.jp/profile/hachioji.html",
    "key": "hachioji",
    "description": "ビックカメラJR八王子駅店の擬人化キャラクター。王子という名前から王冠の髪飾りをしている。制服のリボンは八王子の銀杏がモチーフになっている。",
    "twitter_url": "https://twitter.com/bichachioji",
    "profile_image_url": "https://biccame.jp/profile/images/hachioji1.png",
    "zipcode": "192-0083",
    "address": "東京都八王子市旭町1-17",
    "store_birthday": "2010-11-11",
    "store_link": "http://www.biccamera.co.jp/shoplist/shop-114.html",
    "image_urls": [
      "https://biccame.jp/profile/images/hachi_img.png",
      "https://biccame.jp/profile/images/hachi_img_sd.png",
      "https://biccame.jp/profile/images/hachoji4.png",
      "https://biccame.jp/profile/images/hachioji5.png"
    ]
  },
  {
    "character_name": "ふなたん/船橋たん",
    "store_name": "船橋駅FACE店",
    "detail_url": "https://biccame.jp/profile/funabashi.html",
    "key": "funabashi",
    "description": "ビックカメラ船橋駅FACE店の擬人化キャラクター。いつも髪が跳ねている元気いっぱいの子。ビッカメ娘の中で特にハッピを愛している。制服のリボンと髪飾りに船橋市の花のひまわりをあしらっている。",
    "twitter_url": "https://twitter.com/bic_funabashi",
    "profile_image_url": "https://biccame.jp/profile/images/funabashi1.png",
    "zipcode": "273-0005",
    "address": "千葉県船橋市本町1-3-1",
    "store_birthday": "2010-02-21",
    "store_link": "http://www.biccamera.co.jp/shoplist/shop-109.html",
    "image_urls": [
      "https://biccame.jp/profile/images/huna_img.png",
      "https://biccame.jp/profile/images/huna_img_sd.png",
      "https://biccame.jp/profile/images/funabashi4.png",
      "https://biccame.jp/profile/images/funabashi5.png"
    ]
  },
  {
    "character_name": "しんじゅくたん",
    "store_name": "新宿東口店",
    "detail_url": "https://biccame.jp/profile/bicqlo.html",
    "key": "bicqlo",
    "description": "ビックカメラ新宿東口店の擬人化キャラクター。オッドアイと、他の娘と少し違うデザインの制服が特徴。「～ですわ」とお嬢様口調。新宿の花・ツツジを髪飾りにしている。",
    "twitter_url": "https://twitter.com/bic_shinjuku3ch",
    "profile_image_url": "https://biccame.jp/profile/images/bicqlo1.png",
    "zipcode": "160-0022",
    "address": "東京都新宿区新宿3-29-1",
    "store_birthday": "2012-09-27",
    "store_link": "http://www.biccamera.co.jp/shoplist/shop-116.html",
    "image_urls": [
      "https://biccame.jp/profile/images/biccro_img.png",
      "https://biccame.jp/profile/images/biccro_img_sd.png",
      "https://biccame.jp/profile/images/bicqlo4.png",
      "https://biccame.jp/profile/images/bicqlo5.png"
    ]
  },
  {
    "character_name": "はまたん/浜松たん",
    "store_name": "浜松店",
    "detail_url": "https://biccame.jp/profile/hamamatsu.html",
    "key": "hamamatsu",
    "description": "ビックカメラ浜松店の擬人化キャラクター。のんびりとした性格。うなぎパイが好き。制服のリボンは浜松市の木・松がモチーフ、ヘアピンは市の花・ミカンがモチーフになっている。",
    "twitter_url": "https://twitter.com/bic_hamamatsu",
    "profile_image_url": "https://biccame.jp/profile/images/hama1.png",
    "zipcode": "430-0926",
    "address": "静岡県浜松市中央区砂山町322-1",
    "store_birthday": "2008-11-20",
    "store_link": "http://www.biccamera.co.jp/shoplist/shop-105.html",
    "image_urls": [
      "https://biccame.jp/profile/images/hama_img.png",
      "https://biccame.jp/profile/images/hama_img_sd.png",
      "https://biccame.jp/profile/images/hamamatsu4.png",
      "https://biccame.jp/profile/images/hamamatsu5.png"
    ]
  },
  {
    "character_name": "さがみたん",
    "store_name": "相模大野駅店",
    "detail_url": "https://biccame.jp/profile/sagami.html",
    "key": "sagami",
    "description": "ビックカメラ相模大野駅店の擬人化キャラクター。他の娘より年下。いつも壁からﾁﾗｯしている。ちょっとさみしがり屋な性格。制服のリボンと髪飾りは、相模原市の花のアジサイがモチーフになっている。",
    "twitter_url": "https://twitter.com/bic_sagamioono",
    "profile_image_url": "https://biccame.jp/profile/images/sagami1.png",
    "zipcode": "252-0303",
    "address": "神奈川県相模原市南区相模大野3-8-1",
    "store_birthday": "2010-03-04",
    "store_link": "http://www.biccamera.co.jp/shoplist/shop-108.html",
    "image_urls": [
      "https://biccame.jp/profile/images/sagami_img.png",
      "https://biccame.jp/profile/images/sagami_img_sd.png",
      "https://biccame.jp/profile/images/sagami4.png",
      "https://biccame.jp/profile/images/sagami5.png"
    ]
  },
  {
    "character_name": "本店たん",
    "store_name": "池袋本店",
    "detail_url": "https://biccame.jp/profile/honten.html",
    "key": "honten",
    "description": "ビックカメラ池袋本店の擬人化キャラクター。他の子とは少し違うオーラを放っている。頭のフクロウの方が本体かも知れないという噂も...？袴のような制服が特徴的。",
    "twitter_url": "https://twitter.com/bicikebukuro",
    "profile_image_url": "https://biccame.jp/profile/images/honten1.png",
    "zipcode": "170-0013",
    "address": "東京都豊島区東池袋1-41-5",
    "store_birthday": "1992-09-24",
    "store_link": "http://www.biccamera.co.jp/shoplist/shop-007.html",
    "image_urls": [
      "https://biccame.jp/profile/images/honten_img.png",
      "https://biccame.jp/profile/images/honten_img_sd.png",
      "https://biccame.jp/profile/images/honten4.png",
      "https://biccame.jp/profile/images/honten5.png"
    ]
  },
  {
    "character_name": "プロスタたん",
    "store_name": "ビックフォトスタジオ 東京写真館",
    "detail_url": "https://biccame.jp/profile/prosta.html",
    "key": "prosta",
    "description": "ビックフォトスタジオ東京写真館の擬人化キャラクター。写真を撮ることとコスプレをするのが好き。法被は腰に巻いている。フィルム風のカチューシャは妹とお揃い。",
    "twitter_url": "https://twitter.com/bic_shasinkan",
    "profile_image_url": "https://biccame.jp/profile/images/prosta1.png",
    "zipcode": "171-0021",
    "address": "東京都豊島区西池袋1-16-3",
    "image_urls": [
      "https://biccame.jp/profile/images/pro_img.png",
      "https://biccame.jp/profile/images/pro_img_sd.png",
      "https://biccame.jp/profile/images/prosta4.png",
      "https://biccame.jp/profile/images/shasinkan5.png"
    ]
  },
  {
    "character_name": "大宮たん",
    "store_name": "大宮西口そごう店",
    "detail_url": "https://biccame.jp/profile/ohmiya.html",
    "key": "ohmiya",
    "description": "ビックカメラ大宮西口そごう店の擬人化キャラクター。明るい性格でサッカーが大好き。地元のチームカラーのアイテムをよく集めている。",
    "twitter_url": "https://twitter.com/bic_ohmiya",
    "profile_image_url": "https://biccame.jp/profile/images/ohmiya1.png",
    "zipcode": "330-0854",
    "address": "埼玉県さいたま市大宮区桜木町1-8-4",
    "store_birthday": "2003-11-21",
    "store_link": "http://www.biccamera.co.jp/shoplist/shop-034.html",
    "image_urls": [
      "https://biccame.jp/profile/images/omiya_img.png",
      "https://biccame.jp/profile/images/omiya_img_sd.png",
      "https://biccame.jp/profile/images/ohmiya4.png",
      "https://biccame.jp/profile/images/ohmiya5.png"
    ]
  },
  {
    "character_name": "藤沢たん",
    "store_name": "藤沢店",
    "detail_url": "https://biccame.jp/profile/fujisawa.html",
    "key": "fujisawa",
    "description": "ビックカメラ藤沢店の擬人化キャラクター。ロックでクールなお姉さん。「～だぜ」という口調で話す。イカの触手のような髪は動くという噂も...。ピンクのエクステと藤の花が特徴。",
    "twitter_url": "https://twitter.com/bic_fujisawa",
    "profile_image_url": "https://biccame.jp/profile/images/fujisawa1.png",
    "zipcode": "251-0052",
    "address": "神奈川県藤沢市藤沢559",
    "store_birthday": "2006-08-04",
    "store_link": "http://www.biccamera.co.jp/shoplist/shop-037.html",
    "image_urls": [
      "https://biccame.jp/profile/images/huji_img.png",
      "https://biccame.jp/profile/images/huji_img_sd.png",
      "https://biccame.jp/profile/images/fujisawa4.png",
      "https://biccame.jp/profile/images/fujisawa5.png"
    ]
  },
  {
    "character_name": "フォトたん",
    "store_name": "BIC PHOTO ビックフォト",
    "detail_url": "https://biccame.jp/profile/photo.html",
    "key": "photo",
    "description": "ビックカメラBIC PHOTOの擬人化キャラクター。プロスタたんの妹。お姉ちゃんが撮った写真をプリントしてアルバムにまとめるのが好き。",
    "profile_image_url": "https://biccame.jp/profile/images/photo1.png",
    "image_urls": [
      "https://biccame.jp/profile/images/photo_img.png",
      "https://biccame.jp/profile/images/photo32.png",
      "https://biccame.jp/profile/images/photo4.png",
      "https://biccame.jp/profile/images/photo5.png"
    ]
  },
  {
    "character_name": "なごやたん/名古屋たん",
    "store_name": "名古屋駅西店",
    "detail_url": "https://biccame.jp/profile/nagoya.html",
    "key": "nagoya",
    "description": "ビックカメラ名古屋駅西店の擬人化キャラクター。頭のしゃちほこと、エビフライのようなツインテールが特徴。ギャルっぽい性格。制服のリボンは市の花・ユリがモチーフ。",
    "twitter_url": "https://twitter.com/bic_nagoya",
    "profile_image_url": "https://biccame.jp/profile/images/nagoya_1.png",
    "zipcode": "453-0015",
    "address": "愛知県名古屋市中村区椿町6-9",
    "store_birthday": "2003-11-07",
    "store_link": "http://www.biccamera.co.jp/shoplist/shop-033.html",
    "image_urls": [
      "https://biccame.jp/profile/images/nagoya2.png",
      "https://biccame.jp/profile/images/nagoya32.png",
      "https://biccame.jp/profile/images/nagoya4.png",
      "https://biccame.jp/profile/images/nagoya5.png"
    ]
  },
  {
    "character_name": "有楽町たん",
    "store_name": "有楽町店",
    "detail_url": "https://biccame.jp/profile/yuurakuchou.html",
    "key": "yuurakuchou",
    "description": "ビックカメラ有楽町店の擬人化キャラクター。ビッカメ娘の中でひときわ神々しい存在。少し天然。区の鳥・白鳥のような羽と、着物もようなハッピ、本店たんとお揃いの制服が特徴。",
    "twitter_url": "https://twitter.com/bic_yuurakuchou",
    "profile_image_url": "https://biccame.jp/profile/images/yuurakuchou1%20.png",
    "zipcode": "100-0006",
    "address": "東京都千代田区有楽町1-11-1",
    "store_birthday": "2001-06-14",
    "store_link": "http://www.biccamera.co.jp/shoplist/shop-014.html",
    "image_urls": [
      "https://biccame.jp/profile/images/yuurakuchou.png",
      "https://biccame.jp/profile/images/yuurakuchou21.png",
      "https://biccame.jp/profile/images/yuurakucho4.png",
      "https://biccame.jp/profile/images/yuurakuchou5.png"
    ]
  },
  {
    "character_name": "新宿西口たん",
    "store_name": "新宿西口店",
    "detail_url": "https://biccame.jp/profile/shinjyuku.html",
    "key": "shinjyuku",
    "description": "ビックカメラ新宿西口店の擬人化キャラクター。東口にあるビックロたんと対になるような髪をして、性格も活発的な子。新宿の花・ツツジをアクセサリーにしている。",
    "twitter_url": "https://twitter.com/bic_shinjyuku",
    "profile_image_url": "https://biccame.jp/profile/images/shinjuku.png",
    "zipcode": "160-0023",
    "address": "東京都新宿区西新宿1-5-1",
    "store_birthday": "2002-05-23",
    "store_link": "http://www.biccamera.co.jp/shoplist/shop-016.html",
    "image_urls": [
      "https://biccame.jp/profile/images/shinjuku2.png",
      "https://biccame.jp/profile/images/shinjuku4.png",
      "https://biccame.jp/profile/images/shinjyuku4.png",
      "https://biccame.jp/profile/images/shinjyuku5.png"
    ]
  },
  {
    "character_name": "カメ館たん/カメラ館たん",
    "store_name": "池袋東口カメラ館",
    "detail_url": "https://biccame.jp/profile/camera.html",
    "key": "camera",
    "description": "ビックカメラ池袋東口カメラ館の擬人化キャラクター。同じ池袋の本店たんがお姉ちゃん。リボンとくせっ毛がお揃い。カメラをいつも首からさげている。",
    "profile_image_url": "https://biccame.jp/profile/images/camera1.png",
    "image_urls": [
      "https://biccame.jp/profile/images/camera2.png",
      "https://biccame.jp/profile/4864f8622ad3133a980acfeba567137323f7a6be.png",
      "https://biccame.jp/profile/images/camera4.png",
      "https://biccame.jp/profile/images/camera5.png"
    ]
  },
  {
    "character_name": "パソ館たん/パソコン館たん",
    "store_name": "池袋本店パソコン館",
    "detail_url": "https://biccame.jp/profile/pkan.html",
    "key": "pkan",
    "description": "ビックカメラ本店パソコン館の擬人化キャラクター。同じ池袋の本店たんがお姉ちゃん。リボンとくせっ毛がお揃い。ビルに似たスマホをいつも首からさげている。",
    "twitter_url": "https://twitter.com/bicpkanhonten",
    "profile_image_url": "https://biccame.jp/profile/images/pkan1.png",
    "zipcode": "170-0013",
    "address": "東京都豊島区東池袋1-6-7",
    "store_birthday": "1997-11-27",
    "store_link": "http://www.biccamera.co.jp/shoplist/shop-021.html",
    "image_urls": [
      "https://biccame.jp/profile/images/pkan2.png",
      "https://biccame.jp/profile/pkan3.png",
      "https://biccame.jp/profile/images/pkan4.png",
      "https://biccame.jp/profile/images/pkan5.png"
    ]
  },
  {
    "character_name": "さっぽろたん/札幌たん",
    "store_name": "札幌店",
    "detail_url": "https://biccame.jp/profile/sapporo.html",
    "key": "sapporo",
    "description": "ビックカメラ札幌店の擬人化キャラクター。雪の結晶のピンが宝物。マフラーとブーツが特徴的。みんなから雪の妖精と呼ばれたりしている。",
    "twitter_url": "https://twitter.com/bic_sapporo",
    "profile_image_url": "https://biccame.jp/profile/sapporo1.png",
    "zipcode": "060-8619",
    "address": "北海道札幌市中央区北4条西2-1",
    "store_birthday": "2001-07-26",
    "store_link": "https://www.biccamera.com/bc/i/shop/shoplist/shop132.jsp",
    "image_urls": [
      "https://biccame.jp/profile/sapporo2.png",
      "https://biccame.jp/profile/images/sapporo3.png",
      "https://biccame.jp/profile/images/sapporo4.png",
      "https://biccame.jp/profile/images/sapporo5.png"
    ]
  },
  {
    "character_name": "広島たん",
    "store_name": "広島駅前店",
    "detail_url": "https://biccame.jp/profile/hiroshima.html",
    "key": "hiroshima",
    "description": "ビックカメラ広島駅前店の擬人化キャラクター。もみじと扇子が特徴。「～じゃ」など広島弁がたまに出る。ミステリアスな発言をすることがある。",
    "twitter_url": "https://twitter.com/bic_hiroshima",
    "profile_image_url": "https://biccame.jp/profile/hiroshima2.png",
    "zipcode": "732-0822",
    "address": "広島県広島市南区松原町5-1",
    "store_birthday": "2016-09-14",
    "store_link": "http://www.biccamera.co.jp/shoplist/shop-119.html",
    "image_urls": [
      "https://biccame.jp/profile/hiroshima1.png",
      "https://biccame.jp/profile/images/hiroshima3.png",
      "https://biccame.jp/profile/images/hiroshima4.png",
      "https://biccame.jp/profile/images/hiroshima5.png"
    ]
  },
  {
    "character_name": "せいせきたん/聖蹟たん",
    "store_name": "聖蹟桜ヶ丘駅店",
    "detail_url": "https://biccame.jp/profile/seiseki.html",
    "key": "seiseki",
    "description": "ビックカメラ聖蹟桜ヶ丘駅店の擬人化キャラクター。後ろ髪にある大きな桜の花が特徴。ツイートに桜の花を咲かせるのが得意。",
    "profile_image_url": "https://biccame.jp/profile/seiseki1.png",
    "image_urls": [
      "https://biccame.jp/profile/seiseki2.png",
      "https://biccame.jp/profile/images/seiseki3.png",
      "https://biccame.jp/profile/images/seiseki4.png",
      "https://biccame.jp/profile/images/seiseki5.png"
    ]
  },
  {
    "character_name": "あべのたん",
    "store_name": "あべの キューズモール店",
    "detail_url": "https://biccame.jp/profile/abeno.html",
    "key": "abeno",
    "description": "ビックカメラあべのキューズモール店の擬人化キャラクター。たこ焼きの髪飾り・タコのぬいぐるみ(？)が特徴。青い腕輪はお店のロゴから。",
    "twitter_url": "https://twitter.com/bic_abeno",
    "profile_image_url": "https://biccame.jp/profile/abeno1.png",
    "zipcode": "545-0052",
    "address": "大阪府大阪市阿倍野区阿倍野筋１－６－１",
    "store_birthday": "2016-05-19",
    "store_link": "http://www.biccamera.co.jp/shoplist/shop-118.html",
    "image_urls": [
      "https://biccame.jp/profile/90984e7a605083b17cac42ad3ff95fddedb8c093.png",
      "https://biccame.jp/profile/images/abeno3.png",
      "https://biccame.jp/profile/images/abeno4.png",
      "https://biccame.jp/profile/images/abeno5.png"
    ]
  },
  {
    "character_name": "岡山たん",
    "store_name": "岡山駅前店",
    "detail_url": "https://biccame.jp/profile/okayama.html",
    "key": "okayama",
    "description": "ビックカメラ岡山駅前店の擬人化キャラクター。ポニーテールが桃の形になっている。どこからともなくきびだんごを出す。胸の花はキク。",
    "twitter_url": "https://twitter.com/Bic_Okayamaten",
    "profile_image_url": "https://biccame.jp/profile/okayama1.png",
    "zipcode": "700-0023",
    "address": "岡山県岡山市北区駅前町1-1-1",
    "store_birthday": "2007-11-20",
    "store_link": "http://www.biccamera.co.jp/shoplist/shop-102.html",
    "image_urls": [
      "https://biccame.jp/profile/okayama2.png",
      "https://biccame.jp/profile/okayama3.png",
      "https://biccame.jp/profile/images/okayama4.png",
      "https://biccame.jp/profile/images/okayama5.png"
    ]
  },
  {
    "character_name": "立川たん",
    "store_name": "立川店",
    "detail_url": "https://biccame.jp/profile/tachikawa.html",
    "key": "tachikawa",
    "description": "ビックカメラ立川店の擬人化キャラクター。少しでも背を大きく見せるため大きな帽子を被っている。謎の横髪は立川の名産・ウドをイメージ。胸の花はコブシ。萌え袖が特徴。",
    "twitter_url": "https://twitter.com/bic_tachikawa",
    "profile_image_url": "https://biccame.jp/profile/images/tachikawa1.png",
    "zipcode": "190-0012",
    "address": "東京都立川市曙町2-12-2",
    "store_birthday": "2001-01-26",
    "store_link": "http://www.biccamera.co.jp/shoplist/shop-012.html",
    "image_urls": [
      "https://biccame.jp/profile/images/tachikawa2.png",
      "https://biccame.jp/profile/images/tachikawa3.png",
      "https://biccame.jp/profile/images/tachikawa4.png",
      "https://biccame.jp/profile/images/tachikawa5.png"
    ]
  },
  {
    "character_name": "川崎たん",
    "store_name": "ラゾーナ川崎店",
    "detail_url": "https://biccame.jp/profile/kawasaki.html",
    "key": "kawasaki",
    "description": "ビックカメララゾーナ川崎店の擬人化キャラクター。リボンのようなツインテールと、川崎市の木・ツバキの下にある「川」の文字の様な短冊が特徴。",
    "twitter_url": "https://twitter.com/Bic_kawasaki",
    "profile_image_url": "https://biccame.jp/profile/images/kawasaki1.png",
    "zipcode": "212-0013",
    "address": "神奈川県川崎市幸区堀川町72-１",
    "store_birthday": "2006-09-28",
    "store_link": "http://www.biccamera.co.jp/shoplist/shop-038.html",
    "image_urls": [
      "https://biccame.jp/profile/images/kawasaki2.png",
      "https://biccame.jp/profile/images/kawasaki3.png",
      "https://biccame.jp/profile/images/kawasaki4.png",
      "https://biccame.jp/profile/images/kawasaki5.png"
    ]
  },
  {
    "character_name": "京都たん",
    "store_name": "JR京都駅店",
    "detail_url": "https://biccame.jp/profile/kyoto.html",
    "key": "kyoto",
    "description": "ビックカメラJR京都駅店の擬人化キャラクター。京都の花・ツバキと目元の紅が特徴。神楽鈴を持っている。たまに京都弁が出ることがある。",
    "profile_image_url": "https://biccame.jp/profile/images/kyoto1.png",
    "image_urls": [
      "https://biccame.jp/profile/images/kyoto2.png",
      "https://biccame.jp/profile/images/kyoto3.png",
      "https://biccame.jp/profile/images/kyoto4.png",
      "https://biccame.jp/profile/images/kyoto5.png"
    ]
  },
  {
    "character_name": "なんばたん",
    "store_name": "なんば店",
    "detail_url": "https://biccame.jp/profile/nanba.html",
    "key": "nanba",
    "description": "ビックカメラなんば店の擬人化キャラクター。ヒョウ柄のリボンと、あべのたんとお揃いのたこ焼きの髪飾りが特徴。あべのたんのお姉ちゃん的存在。胸の花はパンジー。",
    "twitter_url": "https://twitter.com/biccamera_nanba",
    "profile_image_url": "https://biccame.jp/profile/images/nanba1.png",
    "zipcode": "542-0074",
    "address": "大阪府大阪市中央区千日前2-10-1",
    "store_birthday": "2001-05-10",
    "store_link": "http://www.biccamera.co.jp/shoplist/shop-013.html",
    "image_urls": [
      "https://biccame.jp/profile/images/nanba2.png",
      "https://biccame.jp/profile/images/nanba3.png",
      "https://biccame.jp/profile/images/nanba4.png",
      "https://biccame.jp/profile/images/nanba5.png"
    ]
  },
  {
    "character_name": "なごやげーとたん",
    "store_name": "名古屋 JRゲートタワー店",
    "detail_url": "https://biccame.jp/profile/nagoyagate.html",
    "key": "nagoyagate",
    "description": "ビックカメラ名古屋JRゲートタワー店の擬人化キャラクター。頭のしゃちほこと、名古屋巻きのような髪型が特徴。制服のリボンは、名古屋たんとは色違いで市の花・ユリがモチーフ。",
    "twitter_url": "https://twitter.com/bic_nagoyagate",
    "profile_image_url": "https://biccame.jp/profile/images/nagoyagate1.png",
    "zipcode": "450-0002",
    "address": "愛知県名古屋市中村区名駅一丁目1番3号",
    "store_birthday": "2017-04-07",
    "store_link": "https://www.biccamera.com/bc/i/shop/shoplist/shop120.jsp",
    "image_urls": [
      "https://biccame.jp/profile/images/nagoyagate2.png",
      "https://biccame.jp/profile/images/nagoyagate3.png",
      "https://biccame.jp/profile/images/nagoyagate4.png",
      "https://biccame.jp/profile/images/nagoyagate5.png"
    ]
  },
  {
    "character_name": "池西たん/池袋西口たん",
    "store_name": "池袋西口店",
    "detail_url": "https://biccame.jp/profile/ikenishi.html",
    "key": "ikenishi",
    "description": "ビックカメラ池袋西口店の擬人化キャラクター。本店たんの妹であり、カメ館パソ館のお姉ちゃんでもある。四姉妹でピンクのリボンをお揃いにしている。",
    "twitter_url": "https://twitter.com/bicikenishi",
    "profile_image_url": "https://biccame.jp/profile/images/ikenishi1.png",
    "zipcode": "171-0021",
    "address": "東京都豊島区西池袋1-16-3",
    "store_birthday": "2002-09-19",
    "store_link": "http://www.biccamera.co.jp/shoplist/shop-017.html",
    "image_urls": [
      "https://biccame.jp/profile/images/ikenishi2.png",
      "https://biccame.jp/profile/images/ikenishi3.png",
      "https://biccame.jp/profile/images/ikenishi4.png",
      "https://biccame.jp/profile/images/ikenishi5.png"
    ]
  },
  {
    "character_name": "アキバたん/秋葉原たん",
    "store_name": "AKIBA",
    "detail_url": "https://biccame.jp/profile/akiba.html",
    "key": "akiba",
    "description": "ビックカメラAKIBAの擬人化キャラクター。千代田区の花・桜がモチーフの大きなリボンと、猫耳のようなヘッドドレスが特徴。",
    "twitter_url": "https://twitter.com/bic_akiba",
    "profile_image_url": "https://biccame.jp/profile/images/akiba1.png",
    "zipcode": "101-0021",
    "address": "東京都千代田区外神田4-1-1",
    "store_birthday": "2017-06-22",
    "store_link": "http://www.biccamera.co.jp/shoplist/shop-121.html",
    "image_urls": [
      "https://biccame.jp/profile/images/akiba2.png",
      "https://biccame.jp/profile/images/akiba3.png",
      "https://biccame.jp/profile/images/akiba4.png",
      "https://biccame.jp/profile/images/akiba5.png"
    ]
  },
  {
    "character_name": "調布たん",
    "store_name": "京王調布店",
    "detail_url": "https://biccame.jp/profile/chofu.html",
    "key": "chofu",
    "description": "ビックカメラ京王調布店の擬人化キャラクター。調布市の花・サルスベリが胸の花のモチーフ。映画が好きで、ビデオカメラをよく持っている。髪はカチンコを意識しているとか...。",
    "twitter_url": "https://twitter.com/bic_keiochofu",
    "profile_image_url": "https://biccame.jp/profile/images/chofu1.png",
    "zipcode": "182-0026",
    "address": "東京都調布市小島町2-48-6",
    "store_birthday": "2017-09-29",
    "store_link": "http://www.biccamera.co.jp/shoplist/shop-122.html",
    "image_urls": [
      "https://biccame.jp/profile/images/chofu2.png",
      "https://biccame.jp/profile/images/chofu3.png",
      "https://biccame.jp/profile/images/chofu4.png",
      "https://biccame.jp/profile/images/chofu5.png"
    ]
  },
  {
    "character_name": "天神2号たん",
    "store_name": "天神2号館",
    "detail_url": "https://biccame.jp/profile/tenjin2.html",
    "key": "tenjin2",
    "description": "ビックカメラ天神2号館の擬人化。頭に飾っているのは福岡市の冬の花・サザンカ。梅の花も好き。",
    "twitter_url": "https://twitter.com/biccameratenjin",
    "profile_image_url": "https://biccame.jp/profile/images/tenjin2go1.png",
    "zipcode": "810-0001",
    "address": "福岡県福岡市中央区天神2-4-5",
    "store_birthday": "2003-03-27",
    "store_link": "http://www.biccamera.co.jp/shoplist/shop-018.html",
    "image_urls": [
      "https://biccame.jp/profile/images/tenjin2go2.png",
      "https://biccame.jp/profile/images/tenjin2go3.png",
      "https://biccame.jp/profile/images/tenjin2go4.png",
      "https://biccame.jp/profile/images/tenjin2go5.png"
    ]
  },
  {
    "character_name": "ふなとーたん",
    "store_name": "船橋東武店",
    "detail_url": "https://biccame.jp/profile/funato.html",
    "key": "funato",
    "description": "ビックカメラ船橋東武店の擬人化キャラクター。制服のリボンのひまわりはふなたんとお揃い。風車のヘアピンをしている。アンデルセンの本が好き。",
    "profile_image_url": "https://biccame.jp/profile/images/funato1.png",
    "image_urls": [
      "https://biccame.jp/profile/images/funato2.png",
      "https://biccame.jp/profile/images/funato3.png",
      "https://biccame.jp/profile/images/funato4.png",
      "https://biccame.jp/profile/images/funato0.png"
    ]
  },
  {
    "character_name": "鹿児島たん",
    "store_name": "鹿児島中央駅店",
    "detail_url": "https://biccame.jp/profile/kagoshima.html",
    "key": "kagoshima",
    "description": "ビックカメラ鹿児島中央駅店の擬人化キャラクター。法被の裏地は宇宙のような柄。大好物はさつまいも。胸の花はキョウチクトウ。髪の色は県の鳥・ルリカケスのような色。",
    "twitter_url": "https://twitter.com/bic_kagoshima",
    "profile_image_url": "https://biccame.jp/profile/images/kagoshima1.png",
    "zipcode": "890-0053",
    "address": "鹿児島県鹿児島市中央町1-1",
    "store_birthday": "2010-02-18",
    "store_link": "http://www.biccamera.co.jp/shoplist/shop-107.html",
    "image_urls": [
      "https://biccame.jp/profile/images/kagoshima2.png",
      "https://biccame.jp/profile/images/kagoshima3.png",
      "https://biccame.jp/profile/images/kagoshima4.png",
      "https://biccame.jp/profile/images/kagoshima5.png"
    ]
  },
  {
    "character_name": "にいがたたん/新潟たん",
    "store_name": "新潟店",
    "detail_url": "https://biccame.jp/profile/niigata.html",
    "key": "niigata",
    "description": "ビックカメラ新潟店の擬人化キャラクター。胸のモチーフは県の花・チューリップと、県の鳥・トキ。お米が大好きで、おにぎりのような形のヘアピンをしている。",
    "twitter_url": "https://twitter.com/niigata_bic",
    "profile_image_url": "https://biccame.jp/profile/images/niigata1.png",
    "zipcode": "950-0086",
    "address": "新潟県新潟市中央区花園1-1-21",
    "store_birthday": "2009-02-20",
    "store_link": "http://www.biccamera.co.jp/shoplist/shop-106.html",
    "image_urls": [
      "https://biccame.jp/profile/images/niigata2.png",
      "https://biccame.jp/profile/images/niigata3.png",
      "https://biccame.jp/profile/images/niigata4.png",
      "https://biccame.jp/profile/images/niigata5.png"
    ]
  },
  {
    "character_name": "みっけたん/赤坂たん",
    "store_name": "赤坂見附駅店",
    "detail_url": "https://biccame.jp/profile/akasaka.html",
    "key": "akasaka",
    "description": "ビックカメラ赤坂見附駅店の擬人化キャラクター。港区の花・バラと、バラに見えるようなお団子の髪型、「3」のようなアホ毛、「坂」のヘアピンが特徴。国際社会にPRできるように、いつもお上品を心掛けている。",
    "twitter_url": "https://twitter.com/bicakasaka",
    "profile_image_url": "https://biccame.jp/profile/images/akasaka1.png",
    "zipcode": "107-0052",
    "address": "東京都港区赤坂3-1-6",
    "store_birthday": "2013-06-07",
    "store_link": "https://www.biccamera.com/bc/i/shop/shoplist/shop117.jsp",
    "image_urls": [
      "https://biccame.jp/profile/images/akasaka2.png",
      "https://biccame.jp/profile/images/akasaka3.png",
      "https://biccame.jp/profile/images/akasaka4.png",
      "https://biccame.jp/profile/images/akasaka5.png"
    ]
  },
  {
    "character_name": "町田たん",
    "store_name": "町田店",
    "detail_url": "https://biccame.jp/profile/machida.html",
    "key": "machida",
    "description": "ビックカメラ町田店の擬人化キャラクター。町田市の花・サルビアと、市の鳥・カワセミのような色の髪が特徴。前髪につけているクロスしたヘアピンと、横で結んだ髪で「町」という字になるようにしている。渋谷とアキバに遊びに行くのが好き。",
    "profile_image_url": "https://biccame.jp/profile/images/machida1.png",
    "image_urls": [
      "https://biccame.jp/profile/images/machida2.png",
      "https://biccame.jp/profile/images/machida3.png",
      "https://biccame.jp/profile/images/machida4.png",
      "https://biccame.jp/profile/images/machida5.png"
    ]
  },
  {
    "character_name": "しぶハチたん",
    "store_name": "渋谷ハチ公口店",
    "detail_url": "https://biccame.jp/profile/shibuhachi.html",
    "key": "shibuhachi",
    "description": "ビックカメラ渋谷ハチ公口店の擬人化キャラクター。渋谷区の花・ハナショウブをモチーフにしたリボンと、犬の耳のような髪型が特徴。犬が大好き。",
    "twitter_url": "https://twitter.com/bicshibuhachi00",
    "profile_image_url": "https://biccame.jp/profile/images/shibuhachi1.png",
    "zipcode": "150-0043",
    "address": "東京都渋谷区道玄坂2-5-9",
    "store_birthday": "1989-12-01",
    "store_link": "https://www.biccamera.com/bc/i/shop/shoplist/shop004.jsp",
    "image_urls": [
      "https://biccame.jp/profile/images/shibuhachi2.png",
      "https://biccame.jp/profile/images/shibuhachi3.png",
      "https://biccame.jp/profile/images/shibuhachi4.png",
      "https://biccame.jp/profile/images/shibuhachi5.png"
    ]
  },
  {
    "character_name": "しぶとーたん",
    "store_name": "渋谷東口店",
    "detail_url": "https://biccame.jp/profile/shibuto.html",
    "key": "shibuto",
    "description": "ビックカメラ渋谷東口店の擬人化キャラクター。渋谷区の花・ハナショウブをモチーフにした髪飾りが特徴。大人っぽい雰囲気が漂っている。実はお絵かきが得意。",
    "twitter_url": "https://twitter.com/bic_shibuya",
    "profile_image_url": "https://biccame.jp/profile/images/shibuto1.png",
    "zipcode": "150-0002",
    "address": "東京都渋谷区渋谷1-24-12",
    "store_birthday": "1993-02-20",
    "store_link": "https://www.biccamera.com/bc/i/shop/shoplist/shop008.jsp",
    "image_urls": [
      "https://biccame.jp/profile/images/shibuto2.png",
      "https://biccame.jp/profile/images/shibuto3.png",
      "https://biccame.jp/profile/images/shibuto4.png",
      "https://biccame.jp/profile/images/shibuto5.png"
    ]
  },
  {
    "character_name": "新横たん",
    "store_name": "新横浜店",
    "detail_url": "https://biccame.jp/profile/shinyoko.html",
    "key": "shinyoko",
    "description": "ビックカメラ新横浜店の擬人化キャラクター。横浜市の花・バラと、マリンカラーな帽子とリボンが特徴。スポーツ観戦が好き。",
    "twitter_url": "https://twitter.com/bic_shinyoko",
    "profile_image_url": "https://biccame.jp/profile/images/shinyoko1.png",
    "zipcode": "222-0033",
    "address": "神奈川県横浜市港北区新横浜2-100-45",
    "store_birthday": "2008-03-26",
    "store_link": "https://www.biccamera.com/bc/i/shop/shoplist/shop104.jsp",
    "image_urls": [
      "https://biccame.jp/profile/images/shinyoko2.png",
      "https://biccame.jp/profile/images/shinyoko3.png",
      "https://biccame.jp/profile/images/shinyoko4.png",
      "https://biccame.jp/profile/images/shinyoko5.png"
    ]
  },
  {
    "character_name": "新東たん",
    "store_name": "新宿東口駅前店",
    "detail_url": "https://biccame.jp/profile/shintou.html",
    "key": "shintou",
    "description": "ビックカメラ新宿東口駅店の擬人化キャラクター。白手袋やニーソックスは、同じく新宿にいるビックロたん・新西たんとおそろい。おっとり優しそうなお姉さん。新宿の花・ツツジをアクセサリーにしている。",
    "twitter_url": "https://twitter.com/Bic_shintoueki",
    "profile_image_url": "https://biccame.jp/profile/images/shintou1.png",
    "zipcode": "160-0022",
    "address": "東京都新宿区新宿3-26-10",
    "store_birthday": "2010-03-03",
    "store_link": "https://www.biccamera.com/bc/i/shop/shoplist/shop111.jsp",
    "image_urls": [
      "https://biccame.jp/profile/images/shintou2.png",
      "https://biccame.jp/profile/images/shintou3.png",
      "https://biccame.jp/profile/images/shintou4.png",
      "https://biccame.jp/profile/images/shintou5.png"
    ]
  },
  {
    "character_name": "たまプラたん",
    "store_name": "イトーヨーカドー たまプラーザ店",
    "detail_url": "https://biccame.jp/profile/tamapla.html",
    "key": "tamapla",
    "description": "ビックカメライトーヨーカドーたまプラーザ店の擬人化キャラクター。青葉が輝くような鮮やかな緑色の髪をポニーテールにしている。ヤマザクラをイメージしたアクセサリーを付けている。大人っぽい雰囲気が漂っている。",
    "profile_image_url": "https://biccame.jp/profile/images/tamapla1.png",
    "image_urls": [
      "https://biccame.jp/profile/images/tamapla2.png",
      "https://biccame.jp/profile/images/tamapla3.png",
      "https://biccame.jp/profile/images/tamapla4.png",
      "https://biccame.jp/profile/images/tamapla5.png"
    ]
  },
  {
    "character_name": "天神1号たん",
    "store_name": "天神1号館",
    "detail_url": "https://biccame.jp/profile/tenjin.html",
    "key": "tenjin",
    "description": "ビックカメラ天神1号館の擬人化。頭に飾っているのは福岡市の夏の花・フヨウ。梅の花も好き。",
    "twitter_url": "https://twitter.com/bic_tenjin",
    "profile_image_url": "https://biccame.jp/profile/images/tenjin1_1.png",
    "zipcode": "810-0021",
    "address": "福岡県福岡市中央区今泉1-25-1",
    "store_birthday": "1999-04-24",
    "store_link": "https://www.biccamera.com/bc/i/shop/shoplist/shop026.jsp",
    "image_urls": [
      "https://biccame.jp/profile/images/tenjin1_2.png",
      "https://biccame.jp/profile/images/tenjin1_3.png",
      "https://biccame.jp/profile/images/tenjin1_4.png",
      "https://biccame.jp/profile/images/tenjin1_5.png"
    ]
  },
  {
    "character_name": "所沢たん/所沢たん",
    "store_name": "所沢駅店",
    "detail_url": "https://biccame.jp/profile/tokorozawa.html",
    "key": "tokorozawa",
    "description": "ビックカメラ所沢駅の擬人化キャラクター。CAさんに憧れており、帽子やスカーフにこだわっている。胸の花は、所沢市の花・茶の花。髪の毛と法被の裏地は空をイメージしている。",
    "twitter_url": "https://twitter.com/bic_toko",
    "profile_image_url": "https://biccame.jp/profile/images/tokorozawa1.png",
    "zipcode": "359-1123",
    "address": "埼玉県所沢市日吉町12-1　西武所沢S.C. 6階",
    "store_birthday": "2019-11-08",
    "store_link": "https://www.biccamera.com/bc/i/shop/shoplist/shop127.jsp",
    "image_urls": [
      "https://biccame.jp/profile/images/tokorozawa2.png",
      "https://biccame.jp/profile/images/tokorozawa3.png",
      "https://biccame.jp/profile/images/tokorozawa4.png",
      "https://biccame.jp/profile/images/tokorozawa5.png"
    ]
  },
  {
    "character_name": "八尾たん/八尾たん",
    "store_name": "アリオ八尾店",
    "detail_url": "https://biccame.jp/profile/yao.html",
    "key": "yao",
    "description": "ビックカメラアリオ八尾店の擬人化キャラクター。髪は八本に分かれている。アーミーなブーツを履いている。胸のリボンは大きなイチョウの葉。",
    "twitter_url": "https://twitter.com/bic_yao",
    "profile_image_url": "https://biccame.jp/profile/images/yao1.png",
    "zipcode": "581-0803",
    "address": "大阪府八尾市光町2-3 アリオ八尾 2F",
    "store_birthday": "2019-07-01",
    "store_link": "https://www.biccamera.com/bc/i/shop/shoplist/shop125.jsp",
    "image_urls": [
      "https://biccame.jp/profile/images/yao2.png",
      "https://biccame.jp/profile/images/yao3.png",
      "https://biccame.jp/profile/images/yao4.png",
      "https://biccame.jp/profile/images/yao5.png"
    ]
  },
  {
    "character_name": "たかつきたん/高槻たん",
    "store_name": "高槻阪急スクエア店",
    "detail_url": "https://biccame.jp/profile/takatsuki.html",
    "key": "takatsuki",
    "description": "ビックカメラ高槻阪急スクエア店の擬人化キャラクター。古風なサイドポニーと勾玉の髪飾りが特徴。関西のビッカメ娘メンバーや、はにわたんとは特に仲良し。胸のモチーフはウノハナ。",
    "twitter_url": "https://twitter.com/bic_takatsuki",
    "profile_image_url": "https://biccame.jp/profile/images/takatsuki1.png",
    "zipcode": "569-1196",
    "address": "大阪府高槻市白梅町4-1 高槻阪急3階",
    "store_birthday": "2022-06-10",
    "store_link": "https://www.biccamera.com/bc/i/shop/shoplist/shop131.jsp",
    "image_urls": [
      "https://biccame.jp/profile/images/takatsuki2.png",
      "https://biccame.jp/profile/images/takatsuki3.png",
      "https://biccame.jp/profile/images/takatsuki4.png",
      "https://biccame.jp/profile/images/takatsuki5.png"
    ]
  },
  {
    "character_name": "千葉たん/千葉たん",
    "store_name": "千葉駅前店",
    "detail_url": "https://biccame.jp/profile/chiba.html",
    "key": "chiba",
    "description": "ビックカメラ千葉駅前店の擬人化キャラクター。エネルギッシュレッドの大きなリボンが特徴。アニメのツンデレキャラに憧れている。相棒のカモメちゃんとは仲良し。胸のモチーフは月と星。",
    "twitter_url": "https://twitter.com/bic_chiba",
    "profile_image_url": "https://biccame.jp/profile/images/chiba1.png",
    "zipcode": "260-0015",
    "address": "千葉県千葉市中央区富士見2-1-1",
    "store_birthday": "2022-11-01",
    "store_link": "https://www.biccamera.com/bc/i/shop/shoplist/shop130.jsp",
    "image_urls": [
      "https://biccame.jp/profile/images/chiba2.png",
      "https://biccame.jp/profile/images/chiba3.png",
      "https://biccame.jp/profile/images/chiba4.png",
      "https://biccame.jp/profile/images/chiba5.png"
    ]
  },
  {
    "character_name": "ビックカメラ",
    "store_name": "ビッカメ娘の舞台",
    "detail_url": "https://biccame.jp/profile/biccamera.html",
    "key": "biccamera",
    "description": "「ビックカメラ」は専門店の集合体！都市型×駅前×大型のお店で便利！ 知識豊富な販売員が親切丁寧にご案内します。カメラ、パソコン、テレビ、家電など、何でも揃う「ビックカメラ」！⇒ビックカメラ",
    "twitter_url": "https://twitter.com/biccameraE",
    "profile_image_url": "https://biccame.jp/profile/images/biccamera1.png",
    "image_urls": [
      "https://biccame.jp/profile/biccamera.png",
      "https://biccame.jp/profile/biccamera3.png"
    ]
  },
  {
    "character_name": "ナイセン",
    "store_name": "ビッカメ娘 企画 公式イラスト",
    "detail_url": "https://biccame.jp/profile/naisen.html",
    "key": "naisen",
    "description": "ビッカメ娘の企画や公式イラストを担当。スマホで03発着信・ナイセンができる「ナイセンクラウド」を運営。主に法人向けの電話サービスではあるが、イラストや動画でアピールしている。⇒ナイセンクラウド⇒なぜナイセンがビッカメ娘を描くのか？ビッカメ娘誕生ストーリーはこちら",
    "twitter_url": "https://twitter.com/itallinc",
    "profile_image_url": "https://biccame.jp/profile/images/itallinc1.png",
    "image_urls": [
      "https://biccame.jp/profile/itallinc.png",
      "https://biccame.jp/profile/itallinc3.png"
    ]
  },
  {
    "character_name": "ビックシムたん",
    "store_name": "ビッカメ娘のお友達？ BIC SIM 擬人化キャラ",
    "detail_url": "https://biccame.jp/profile/bicsim.html",
    "key": "bicsim",
    "description": "BICSIMの擬人化キャラクター。先輩の「シムウマ」を尊敬していて、スマホにキーホルダーを付けたり、ウマ耳を真似している。もっともっと人と人とが繋がれるように「BIC SIM」 を知ってもらい、使ってもらう！のがモットー。",
    "twitter_url": "https://twitter.com/bicsim_official",
    "profile_image_url": "https://biccame.jp/profile/images/bicsim1.png",
    "image_urls": [
      "https://biccame.jp/profile/images/bicsim2.png",
      "https://biccame.jp/profile/images/bicsim3.png"
    ]
  },
  {
    "character_name": "お偉いたん",
    "store_name": "ビッカメ娘を見守る お偉いたん",
    "detail_url": "https://biccame.jp/profile/oeraitan.html",
    "key": "oeraitan",
    "description": "ビックカメラのお偉いたんです。あくまでもビッカメ娘達の行動を影から見守る少し恥ずかしがりやなお偉いたんです。",
    "profile_image_url": "https://biccame.jp/profile/images/oeraitan1.png",
    "image_urls": [
      "https://biccame.jp/profile/oeraitan.png",
      "https://biccame.jp/profile/images/oeraitan3.png"
    ]
  }
]
